exportrecipe.py
exportrecipe-0.2.dist-info/DESCRIPTION.rst
exportrecipe-0.2.dist-info/top_level.txt
exportrecipe-0.2.dist-info/metadata.json
exportrecipe-0.2.dist-info/RECORD
exportrecipe-0.2.dist-info/METADATA
exportrecipe-0.2.dist-info/WHEEL
exportrecipe-0.2.dist-info/entry_points.txt
