Metadata-Version: 2.0
Name: exportrecipe
Version: 0.2
Summary: Buildout recipe to export buildout configuration to JSON file.
Home-page: https://bitbucket.org/sirex/rubygemsrecipe
Author: Mantas Zimnickas
Author-email: sirexas@gmail.com
License: MIT
Platform: UNKNOWN
Classifier: Framework :: Buildout :: Recipe
Classifier: Intended Audience :: Developers
Classifier: Intended Audience :: System Administrators
Classifier: Topic :: Software Development
Classifier: License :: OSI Approved :: MIT License
Classifier: Programming Language :: Python :: 2
Classifier: Programming Language :: Python :: 3
Requires-Dist: zc.buildout
Provides-Extra: tests
Requires-Dist: mock; extra == 'tests'
